nandai/__init__.py
nandai/api.py
nandai/constants.py
nandai/utils.py
nandai/validator.py
nandai/scripts/cli.py
nandai-0.1.11.dist-info/METADATA
nandai-0.1.11.dist-info/WHEEL
nandai-0.1.11.dist-info/entry_points.txt
nandai-0.1.11.dist-info/RECORD
