Metadata-Version: 2.1
Name: nandai
Version: 0.1.11
Summary: Nand AI Python SDK
Author-email: Martin Liu <martin@nand.ai>
Requires-Python: >=3.8
Requires-Dist: httpx>=0.25.1
Requires-Dist: itables>=1.6.2
Requires-Dist: pandas
Requires-Dist: tqdm>=4.66.1
Requires-Dist: typer>=0.9.0
